cemd_metasurf/__init__.py
cemd_metasurf/my_metasurface.py
cemd_metasurf/depolarization_gf/__init__.py
cemd_metasurf/depolarization_gf/depolarization_functions.py
cemd_metasurf/depolarization_gf/depolarization_gf.py
cemd_metasurf/polarizability/__init__.py
cemd_metasurf/polarizability/mie_functions.py
cemd_metasurf/reflec_transm/__init__.py
cemd_metasurf/reflec_transm/reflec_transm.py
cemd_metasurf/reflec_transm/rt_functions.py
cemd_metasurf-0.1.2.dist-info/LICENSE
cemd_metasurf-0.1.2.dist-info/METADATA
cemd_metasurf-0.1.2.dist-info/WHEEL
cemd_metasurf-0.1.2.dist-info/top_level.txt
cemd_metasurf-0.1.2.dist-info/RECORD
