Metadata-Version: 2.1
Name: cemd-metasurf
Version: 0.1.2
Summary: Optical properties of metasurfaces made of dipolar particles
Author: Diego Romero Abujetas
License: MIT
Platform: UNKNOWN
License-File: LICENSE
Requires-Dist: numpy
